streamlit_float/__init__.py
streamlit_float/demo.py
streamlit_float/test.py
streamlit_float-0.3.3.dist-info/LICENSE.txt
streamlit_float-0.3.3.dist-info/METADATA
streamlit_float-0.3.3.dist-info/WHEEL
streamlit_float-0.3.3.dist-info/top_level.txt
streamlit_float-0.3.3.dist-info/RECORD
