Metadata-Version: 2.1
Name: streamlit-float
Version: 0.3.3
Summary: Fix Streamlit containers relative to viewport instead of page
Home-page: https://github.com/bouzidanas/streamlit-float
Author: Anas Bouzid
Author-email: anasbouzid@gmail.com
License: UNKNOWN
Platform: UNKNOWN
Requires-Python: >=3.6
License-File: LICENSE.txt
Requires-Dist: streamlit (>=0.63)
